Workbook
Name Slicer_Category: #N/A
Name Slicer_Product_Name: #N/A

Sheet Project Instructions
A1: PR. Final Project - "Data Intelligence Dashboard"
A2: Dataset: Use the 'Final Project Dataset' sheet containing 200+ records of customer transactions. Objective: Create a full-fledged analysis and reporting solution using Excel to analyze customer transactions, find insights, and build visualizations and dashboards. Key Topics to Implement: - Date & Time Functions: TODAY, NOW, DATEDIF, EOMONTH - FILTER Function for multi-value returns - Conditional Formatting with Icons/Arrows - Create Timestamp (using NOW and iterative calculations) - WHAT-IF Analysis: Scenario Manager, Goal Seek - Linear Regression using Data Analysis Toolpak - Data Analysis & Storytelling from the dataset - Use GroupBy concepts to find High-Value Customers using formulas - Create Dashboard using: - Pivot Tables - Pivot Charts (Bar, Line, Pie) - Slicers and Timelines - KPI Indicators with Conditional Formatting - Find most frequently purchased product or repeating names using formulas - Compare two lists and extract matching names in a new column - Create Abbreviations using TEXT functions - Build a final report with insights and storytelling Deliverable: - Well-structured workbook with multiple sheets (Raw Data, Analysis, Visualizations, Dashboard) - Summary Insights with key metrics: Total Revenue, Top Customers, Most Sold Products, Regional Sales - Use of all required formulas and functions as listed above

Sheet pivot_table
A3: Sum of Total_Amount | C3: Row Labels | D3: Sum of Total_Amount | F3: Row Labels | G3: Sum of Total_Amount
A4: 229192.47 | C4: Central | D4: 41288.34 | F4: Jennifer Taylor | G4: 639.92
C5: East | D5: 59288.39 | F5: Lisa Anderson | G5: 539.92
C6: North | D6: 50808.31 | F6: David Martinez | G6: 519.93
C7: South | D7: 36398.75 | F7: Dennis Gray | G7: 479.92
C8: West | D8: 41408.68 | F8: Sharon Butler | G8: 419.93
C9: Grand Total | D9: 229192.47 | F9: Helen Roberts | G9: 359.95
F10: Cynthia Price | G10: 319.96
F11: Paul Baker | G11: 299.95
F12: Emma Wilson | G12: 299.95
F13: Charles Allen | G13: 259.96
F14: Kevin Scott | G14: 259.96
F15: Grand Total | G15: 4399.35
D16: Row Labels | E16: Sum of Total_Amount
D17: Jan | E17: 449.97
D18: Feb | E18: 1799.88
D19: Mar | E19: 2549.83
D20: Apr | E20: 2699.82
D21: May | E21: 749.95
D22: Jun | E22: 449.97
D23: Jul | E23: 599.96
D24: Aug | E24: 1349.91
D25: Sep | E25: 449.97
D26: Oct | E26: 449.97
D27: Nov | E27: 2099.86
D28: Dec | E28: 1649.89
D29: Grand Total | E29: 15298.98

Sheet filter
A1: Transaction_ID | B1: Date | C1: Customer_ID | D1: Customer_Name | E1: Product_ID | F1: Product_Name | G1: Category | H1: Quantity | I1: Unit_Price | J1: Payment_Method | K1: Region | L1: Customer_Segment | M1: Customer_Since | N1: Total_Amount
A2: {=_xlfn._xlws.FILTER(Table2[[Transaction_ID]:[Total_Amount]], Table2[Category]="Electronics")} -> TRX0155 | B2: 45393 | C2: CUST023 | D2: Paul Baker | E2: P009 | F2: Monitor | G2: Electronics | H2: 3 | I2: 249.99 | J2: Cash | K2: Central | L2: Basic | M2: 44425 | N2: 749.97
A3: TRX0023 | B3: 45396 | C3: CUST013 | D3: Joseph Jackson | E3: P009 | F3: Monitor | G3: Electronics | H3: 3 | I3: 249.99 | J3: Credit Card | K3: Central | L3: Premium | M3: 44575 | N3: 749.97
A4: TRX0193 | B4: 45403 | C4: CUST024 | D4: Dorothy Nelson | E4: P003 | F4: Headphones | G4: Electronics | H4: 5 | I4: 149.99 | J4: Credit Card | K4: Central | L4: Standard | M4: 44418 | N4: 749.95
A5: TRX0135 | B5: 45405 | C5: CUST009 | D5: Robert Thomas | E5: P001 | F5: Laptop | G5: Electronics | H5: 3 | I5: 899.99 | J5: PayPal | K5: East | L5: Standard | M5: 45299 | N5: 2699.97
A6: TRX0191 | B6: 45409 | C6: CUST038 | D6: Michelle Rogers | E6: P002 | F6: Smartphone | G6: Electronics | H6: 3 | I6: 699.99 | J6: Credit Card | K6: West | L6: Basic | M6: 44577 | N6: 2099.97
A7: TRX0230 | B7: 45409 | C7: CUST027 | D7: George Adams | E7: P001 | F7: Laptop | G7: Electronics | H7: 1 | I7: 899.99 | J7: Debit Card | K7: North | L7: Standard | M7: 44920 | N7: 899.99
A8: TRX0134 | B8: 45410 | C8: CUST010 | D8: Maria Garcia | E8: P002 | F8: Smartphone | G8: Electronics | H8: 2 | I8: 699.99 | J8: Cash | K8: North | L8: Basic | M8: 44781 | N8: 1399.98
A9: TRX0122 | B9: 45410 | C9: CUST025 | D9: Mark Carter | E9: P001 | F9: Laptop | G9: Electronics | H9: 4 | I9: 899.99 | J9: Credit Card | K9: West | L9: Standard | M9: 45327 | N9: 3599.96
A10: TRX0222 | B10: 45410 | C10: CUST048 | D10: Virginia Sanders | E10: P009 | F10: Monitor | G10: Electronics | H10: 3 | I10: 249.99 | J10: Credit Card | K10: North | L10: Premium | M10: 45224 | N10: 749.97
A11: TRX0231 | B11: 45412 | C11: CUST018 | D11: Barbara Young | E11: P002 | F11: Smartphone | G11: Electronics | H11: 5 | I11: 699.99 | J11: Cash | K11: West | L11: Basic | M11: 45167 | N11: 3499.95
A12: TRX0239 | B12: 45413 | C12: CUST012 | D12: Patricia Moore | E12: P002 | F12: Smartphone | G12: Electronics | H12: 4 | I12: 699.99 | J12: Cash | K12: East | L12: Standard | M12: 44409 | N12: 2799.96
A13: TRX0204 | B13: 45415 | C13: CUST044 | D13: Cynthia Price | E13: P009 | F13: Monitor | G13: Electronics | H13: 4 | I13: 249.99 | J13: PayPal | K13: North | L13: Standard | M13: 44468 | N13: 999.96
A14: TRX0071 | B14: 45422 | C14: CUST036 | D14: Nancy Collins | E14: P009 | F14: Monitor | G14: Electronics | H14: 5 | I14: 249.99 | J14: Credit Card | K14: West | L14: Standard | M14: 44525 | N14: 1249.95
... A132: TRX0064 | B132: 45758 | C132: CUST031 | D132: Steven Turner | E132: P010 | F132: Keyboard | G132: Electronics | H132: 3 | I132: 89.99 | J132: Debit Card | K132: North | L132: Premium | M132: 44878 | N132: 269.97

Sheet dataset
A1: Transaction_ID | B1: Date | C1: Customer_ID | D1: Customer_Name | E1: Product_ID | F1: Product_Name | G1: Category | H1: Quantity | I1: Unit_Price | J1: Payment_Method | K1: Region | L1: Customer_Segment | M1: Customer_Since | N1: Total_Amount | O1: month | P1: Column2 | Q1: Column3 | R1: product quantity | U1: Transaction_ID | V1: Date | W1: Customer_ID | X1: Customer_Name | Y1: Product_ID | Z1: Product_Name | AA1: Category | AB1: Quantity | AC1: Unit_Price | AD1: Payment_Method | AE1: Region | AF1: Customer_Segment | AG1: Customer_Since | AH1: Total_Amount | AI1: time stamp | AJ1: year from | AK1: end of month
A2: TRX0155 | B2: 45393 | C2: CUST023 | D2: Paul Baker | E2: P009 | F2: Monitor | G2: Electronics | H2: 3 | I2: 249.99 | J2: Cash | K2: Central | L2: Basic | M2: 44425 | N2: 749.97 | O2: =TEXT(Table2[[#This Row],[Date]],"mmm") -> Apr | R2: =SUMIF(Table2[Product_Name],F4,Table2[[#All],[Quantity]]) -> 98
A3: TRX0023 | B3: 45396 | C3: CUST013 | D3: Joseph Jackson | E3: P009 | F3: Monitor | G3: Electronics | H3: 3 | I3: 249.99 | J3: Credit Card | K3: Central | L3: Premium | M3: 44575 | N3: 749.97 | O3: =TEXT(Table2[[#This Row],[Date]],"mmm") -> Apr | R3: =SUMIF(Table2[Product_Name],F5,Table2[[#All],[Quantity]]) -> 98
A4: TRX0139 | B4: 45399 | C4: CUST021 | D4: Kevin Scott | E4: P005 | F4: Blender | G4: Appliances | H4: 3 | I4: 59.99 | J4: PayPal | K4: South | L4: Standard | M4: 45262 | N4: 179.97 | O4: =TEXT(Table2[[#This Row],[Date]],"mmm") -> Apr | R4: =SUMIF(Table2[Product_Name],F6,Table2[[#All],[Quantity]]) -> 108
A5: TRX0043 | B5: 45400 | C5: CUST046 | D5: Kathleen Bennett | E5: P005 | F5: Blender | G5: Appliances | H5: 3 | I5: 59.99 | J5: Cash | K5: North | L5: Premium | M5: 45114 | N5: 179.97 | O5: =TEXT(Table2[[#This Row],[Date]],"mmm") -> Apr | R5: =SUMIF(Table2[Product_Name],F7,Table2[[#All],[Quantity]]) -> 98
A6: TRX0212 | B6: 45400 | C6: CUST003 | D6: Michael Brown | E6: P008 | F6: Bookshelf | G6: Furniture | H6: 5 | I6: 149.99 | J6: Credit Card | K6: North | L6: Premium | M6: 45295 | N6: 749.95 | O6: =TEXT(Table2[[#This Row],[Date]],"mmm") -> Apr | R6: =SUMIF(Table2[Product_Name],F8,Table2[[#All],[Quantity]]) -> 48
A7: TRX0092 | B7: 45403 | C7: CUST024 | D7: Dorothy Nelson | E7: P005 | F7: Blender | G7: Appliances | H7: 2 | I7: 59.99 | J7: Cash | K7: West | L7: Standard | M7: 44746 | N7: 119.98 | O7: =TEXT(Table2[[#This Row],[Date]],"mmm") -> Apr | R7: =SUMIF(Table2[Product_Name],F9,Table2[[#All],[Quantity]]) -> 98
A8: TRX0193 | B8: 45403 | C8: CUST024 | D8: Dorothy Nelson | E8: P003 | F8: Headphones | G8: Electronics | H8: 5 | I8: 149.99 | J8: Credit Card | K8: Central | L8: Standard | M8: 44418 | N8: 749.95 | O8: =TEXT(Table2[[#This Row],[Date]],"mmm") -> Apr | R8: =SUMIF(Table2[Product_Name],F10,Table2[[#All],[Quantity]]) -> 67
A9: TRX0240 | B9: 45403 | C9: CUST017 | D9: Charles Allen | E9: P005 | F9: Blender | G9: Appliances | H9: 3 | I9: 59.99 | J9: Debit Card | K9: South | L9: Basic | M9: 45007 | N9: 179.97 | O9: =TEXT(Table2[[#This Row],[Date]],"mmm") -> Apr | R9: =SUMIF(Table2[Product_Name],F11,Table2[[#All],[Quantity]]) -> 98
A10: TRX0135 | B10: 45405 | C10: CUST009 | D10: Robert Thomas | E10: P001 | F10: Laptop | G10: Electronics | H10: 3 | I10: 899.99 | J10: PayPal | K10: East | L10: Standard | M10: 45299 | N10: 2699.97 | O10: =TEXT(Table2[[#This Row],[Date]],"mmm") -> Apr | R10: =SUMIF(Table2[Product_Name],F12,Table2[[#All],[Quantity]]) -> 108
A11: TRX0185 | B11: 45408 | C11: CUST026 | D11: Karen Hill | E11: P005 | F11: Blender | G11: Appliances | H11: 3 | I11: 59.99 | J11: Cash | K11: West | L11: Premium | M11: 45207 | N11: 179.97 | O11: =TEXT(Table2[[#This Row],[Date]],"mmm") -> Apr | R11: =SUMIF(Table2[Product_Name],F13,Table2[[#All],[Quantity]]) -> 108
A12: TRX0138 | B12: 45408 | C12: CUST022 | D12: Susan Green | E12: P008 | F12: Bookshelf | G12: Furniture | H12: 1 | I12: 149.99 | J12: Credit Card | K12: West | L12: Standard | M12: 45103 | N12: 149.99 | O12: =TEXT(Table2[[#This Row],[Date]],"mmm") -> Apr | R12: =SUMIF(Table2[Product_Name],F14,Table2[[#All],[Quantity]]) -> 108
A13: TRX0209 | B13: 45408 | C13: CUST046 | D13: Kathleen Bennett | E13: P008 | F13: Bookshelf | G13: Furniture | H13: 5 | I13: 149.99 | J13: Debit Card | K13: North | L13: Basic | M13: 44830 | N13: 749.95 | O13: =TEXT(Table2[[#This Row],[Date]],"mmm") -> Apr | R13: =SUMIF(Table2[Product_Name],F15,Table2[[#All],[Quantity]]) -> 98
... A251: TRX0064 | B251: 45758 | C251: CUST031 | D251: Steven Turner | E251: P010 | F251: Keyboard | G251: Electronics | H251: 3 | I251: 89.99 | J251: Debit Card | K251: North | L251: Premium | M251: 44878 | N251: 269.97 | O251: =TEXT(Table2[[#This Row],[Date]],"mmm") -> Apr | R251: =SUMIF(Table2[Product_Name],F253,Table2[[#All],[Quantity]]) -> 0

Sheet linear regression
A1: SUMMARY OUTPUT
A3: Regression Statistics
A4: Multiple R | B4: 0.45808036
A5: R Square | B5: 0.20983762
A6: Adjusted R Square | B6: 0.20665148
A7: Standard Error | B7: 919.60715
A8: Observations | B8: 250
A10: ANOVA
B11: df | C11: SS | D11: MS | E11: F | F11: Significance F
A12: Regression | B12: 1 | C12: 55695917 | D12: 55695917 | E12: 65.859537 | F12: 2.2586479e-14
A13: Residual | B13: 248 | C13: 2.0972797e+08 | D13: 845677.32
A14: Total | B14: 249 | C14: 2.6542389e+08
B16: Coefficients | C16: Standard Error | D16: t Stat | E16: P-value | F16: Lower 95% | G16: Upper 95% | H16: Lower 95.0% | I16: Upper 95.0%
A17: Intercept | B17: -148.85465 | C17: 143.61334 | D17: -1.0364959 | E17: 0.3009804 | F17: -431.712 | G17: 134.0027 | H17: -431.712 | I17: 134.0027
A18: X Variable 1 | B18: 353.793 | C18: 43.595323 | D18: 8.1153889 | E18: 2.2586479e-14 | F18: 267.92872 | G18: 439.65729 | H18: 267.92872 | I18: 439.65729

Sheet dashboard
A2: Total sales | B2: =SUM(Table2[Total_Amount]) -> 229192.47 | F2: Average | G2: =AVERAGE(Table2[Total_Amount]) -> 916.76988 | J2: Total customers | K2: =COUNTA(_xlfn.UNIQUE(Table2[Customer_ID])) -> 50 | M2: Total orders | O2: =COUNTA(Table2[Transaction_ID]) -> 250

Sheet date_time
A1: time stamp | B1: year from | C1: end of month
A2: =NOW() -> 46083.053 | B2: =DATEDIF(Table2[[#This Row],[Customer_Since]], TODAY(), "Y") -> 4 | C2: =EOMONTH(Table2[[#This Row],[Date]],0) -> 45412
A3: =NOW() -> 46083.053 | B3: =DATEDIF(Table2[[#This Row],[Customer_Since]], TODAY(), "Y") -> 4 | C3: =EOMONTH(Table2[[#This Row],[Date]],0) -> 45412
A4: =NOW() -> 46083.053 | B4: =DATEDIF(Table2[[#This Row],[Customer_Since]], TODAY(), "Y") -> 2 | C4: =EOMONTH(Table2[[#This Row],[Date]],0) -> 45412
A5: =NOW() -> 46083.053 | B5: =DATEDIF(Table2[[#This Row],[Customer_Since]], TODAY(), "Y") -> 2 | C5: =EOMONTH(Table2[[#This Row],[Date]],0) -> 45412
A6: =NOW() -> 46083.053 | B6: =DATEDIF(Table2[[#This Row],[Customer_Since]], TODAY(), "Y") -> 2 | C6: =EOMONTH(Table2[[#This Row],[Date]],0) -> 45412
A7: =NOW() -> 46083.053 | B7: =DATEDIF(Table2[[#This Row],[Customer_Since]], TODAY(), "Y") -> 3 | C7: =EOMONTH(Table2[[#This Row],[Date]],0) -> 45412
A8: =NOW() -> 46083.053 | B8: =DATEDIF(Table2[[#This Row],[Customer_Since]], TODAY(), "Y") -> 4 | C8: =EOMONTH(Table2[[#This Row],[Date]],0) -> 45412
A9: =NOW() -> 46083.053 | B9: =DATEDIF(Table2[[#This Row],[Customer_Since]], TODAY(), "Y") -> 2 | C9: =EOMONTH(Table2[[#This Row],[Date]],0) -> 45412
A10: =NOW() -> 46083.053 | B10: =DATEDIF(Table2[[#This Row],[Customer_Since]], TODAY(), "Y") -> 2 | C10: =EOMONTH(Table2[[#This Row],[Date]],0) -> 45412
A11: =NOW() -> 46083.053 | B11: =DATEDIF(Table2[[#This Row],[Customer_Since]], TODAY(), "Y") -> 2 | C11: =EOMONTH(Table2[[#This Row],[Date]],0) -> 45412
A12: =NOW() -> 46083.053 | B12: =DATEDIF(Table2[[#This Row],[Customer_Since]], TODAY(), "Y") -> 2 | C12: =EOMONTH(Table2[[#This Row],[Date]],0) -> 45412
A13: =NOW() -> 46083.053 | B13: =DATEDIF(Table2[[#This Row],[Customer_Since]], TODAY(), "Y") -> 3 | C13: =EOMONTH(Table2[[#This Row],[Date]],0) -> 45412
... A251: =NOW() -> 46083.053 | B251: =DATEDIF(Table2[[#This Row],[Customer_Since]], TODAY(), "Y") -> 3 | C251: =EOMONTH(Table2[[#This Row],[Date]],0) -> 45777

Sheet what if analysis
A3: WHAT-IF ANALYSIS - SCENARIO MANAGER
A5: Base Total Revenue | B5: =SUM('[1]Final Project Dataset'!N:N) -> 229192.47
A7: Scenario | B7: Price Change % | C7: Adjusted Revenue
A8: Best Case | B8: 0.1 | C8: =B5*(1+B8) -> 252111.72
A9: Normal Case | B9: 0 | C9: =B5*(1+B9) -> 229192.47
A10: Worst Case | B10: -0.1 | C10: =B5*(1+B10) -> 206273.22

Sheet total quantity
A1: Product_Name | B1: product quantity | D1: cu product
A2: Monitor | B2: =SUMIF(Table2[Product_Name],Table2[[#This Row],[Product_Name]],dataset!H:H) -> 86 | D2: =COUNTIF(Table2[Product_Name],Table2[[#This Row],[Product_Name]]) -> 26
A3: Monitor | B3: =SUMIF(Table2[Product_Name],Table2[[#This Row],[Product_Name]],dataset!H:H) -> 86 | D3: =COUNTIF(Table2[Product_Name],Table2[[#This Row],[Product_Name]]) -> 26
A4: Blender | B4: =SUMIF(Table2[Product_Name],Table2[[#This Row],[Product_Name]],dataset!H:H) -> 98 | D4: =COUNTIF(Table2[Product_Name],Table2[[#This Row],[Product_Name]]) -> 29
A5: Blender | B5: =SUMIF(Table2[Product_Name],Table2[[#This Row],[Product_Name]],dataset!H:H) -> 98 | D5: =COUNTIF(Table2[Product_Name],Table2[[#This Row],[Product_Name]]) -> 29
A6: Bookshelf | B6: =SUMIF(Table2[Product_Name],Table2[[#This Row],[Product_Name]],dataset!H:H) -> 108 | D6: =COUNTIF(Table2[Product_Name],Table2[[#This Row],[Product_Name]]) -> 35
A7: Blender | B7: =SUMIF(Table2[Product_Name],Table2[[#This Row],[Product_Name]],dataset!H:H) -> 98 | D7: =COUNTIF(Table2[Product_Name],Table2[[#This Row],[Product_Name]]) -> 29
A8: Headphones | B8: =SUMIF(Table2[Product_Name],Table2[[#This Row],[Product_Name]],dataset!H:H) -> 48 | D8: =COUNTIF(Table2[Product_Name],Table2[[#This Row],[Product_Name]]) -> 16
A9: Blender | B9: =SUMIF(Table2[Product_Name],Table2[[#This Row],[Product_Name]],dataset!H:H) -> 98 | D9: =COUNTIF(Table2[Product_Name],Table2[[#This Row],[Product_Name]]) -> 29
A10: Laptop | B10: =SUMIF(Table2[Product_Name],Table2[[#This Row],[Product_Name]],dataset!H:H) -> 67 | D10: =COUNTIF(Table2[Product_Name],Table2[[#This Row],[Product_Name]]) -> 24
A11: Blender | B11: =SUMIF(Table2[Product_Name],Table2[[#This Row],[Product_Name]],dataset!H:H) -> 98 | D11: =COUNTIF(Table2[Product_Name],Table2[[#This Row],[Product_Name]]) -> 29
A12: Bookshelf | B12: =SUMIF(Table2[Product_Name],Table2[[#This Row],[Product_Name]],dataset!H:H) -> 108 | D12: =COUNTIF(Table2[Product_Name],Table2[[#This Row],[Product_Name]]) -> 35
A13: Bookshelf | B13: =SUMIF(Table2[Product_Name],Table2[[#This Row],[Product_Name]],dataset!H:H) -> 108 | D13: =COUNTIF(Table2[Product_Name],Table2[[#This Row],[Product_Name]]) -> 35
... A251: Keyboard | B251: =SUMIF(Table2[Product_Name],Table2[[#This Row],[Product_Name]],dataset!H:H) -> 99 | D251: =COUNTIF(Table2[Product_Name],Table2[[#This Row],[Product_Name]]) -> 34
